scons517-0.0.1.post2.dist-info/METADATA
scons517-0.0.1.post2.dist-info/WHEEL
scons517-0.0.1.post2.dist-info/entry_points.txt
scons517/__init__.py
scons517/api.py
scons517/extension.py
scons517/pytar.py
scons517/sphinx.py
scons517/wheel.py
scons517-0.0.1.post2.dist-info/RECORD