Metadata-Version: 2.1
Name: scons517
Version: 0.0.1.post2
Summary: Pep 517 compliant Python Distribution Wheel Builder
Requires-Python: >=3.8
Author-Email: Andrew Brown <andrew@brownan.org>
Classifier: Development Status :: 4 - Beta
Classifier: License :: OSI Approved :: MIT License
Classifier: Topic :: Software Development :: Build Tools
Project-URL: Source Code, https://github.com/brownan/scons517
Requires-Dist: SCons==4.4.0
Requires-Dist: packaging
Requires-Dist: toml
Provides-Extra: dev
Requires-Dist: pre-commit; extra == 'dev'
Requires-Dist: mypy; extra == 'dev'
Requires-Dist: sphinx; extra == 'dev'
Requires-Dist: furo; extra == 'dev'
Requires-Dist: types-toml; extra == 'dev'
